ibm_scc/__init__.py
ibm_scc/common.py
ibm_scc/security_and_compliance_center_api_v3.py
ibm_scc/version.py
ibm_scc-5.0.0.dist-info/licenses/LICENSE
ibm_scc-5.0.0.dist-info/METADATA
ibm_scc-5.0.0.dist-info/WHEEL
ibm_scc-5.0.0.dist-info/top_level.txt
ibm_scc-5.0.0.dist-info/zip-safe
ibm_scc-5.0.0.dist-info/RECORD
